unsent/__init__.py
unsent/activity.py
unsent/analytics.py
unsent/api_keys.py
unsent/campaigns.py
unsent/contact_books.py
unsent/contacts.py
unsent/domains.py
unsent/emails.py
unsent/events.py
unsent/legacy_types.py
unsent/metrics.py
unsent/py.typed
unsent/settings.py
unsent/stats.py
unsent/suppressions.py
unsent/system.py
unsent/teams.py
unsent/templates.py
unsent/types.py
unsent/unsent.py
unsent/webhooks.py
unsent-1.0.3.dist-info/METADATA
unsent-1.0.3.dist-info/WHEEL
unsent-1.0.3.dist-info/licenses/LICENSE
unsent-1.0.3.dist-info/RECORD
