Metadata-Version: 2.4
Name: unsent
Version: 1.0.3
Summary: Python SDK for the Unsent API - Send transactional emails with ease
License: MIT
License-File: LICENSE
Keywords: unsent,email,transactional-email,api,sdk
Author: sourav
Requires-Python: >=3.10,<4.0
Classifier: License :: OSI Approved :: MIT License
Classifier: Programming Language :: Python :: 3
Classifier: Programming Language :: Python :: 3.10
Classifier: Programming Language :: Python :: 3.11
Classifier: Programming Language :: Python :: 3.12
Classifier: Programming Language :: Python :: 3.13
Classifier: Programming Language :: Python :: 3.14
Requires-Dist: pydantic[email] (>=2.12.5,<3.0.0)
Requires-Dist: requests (>=2.32.0,<3.0.0)
Requires-Dist: typing_extensions (>=4.7)
Project-URL: Documentation, https://docs.unsent.dev
Project-URL: Homepage, https://unsent.dev
Project-URL: Repository, https://github.com/souravsspace/unsent-python
